traxgen/__init__.py
traxgen/api.py
traxgen/data_creation.py
traxgen/multi_agent.py
traxgen/parser.py
traxgen/planner.py
traxgen/utils.py
traxgen/validator.py
traxgen/visualizer.py
traxgen-0.1.5.dist-info/licenses/LICENSE
traxgen-0.1.5.dist-info/METADATA
traxgen-0.1.5.dist-info/WHEEL
traxgen-0.1.5.dist-info/top_level.txt
traxgen-0.1.5.dist-info/RECORD
