Metadata-Version: 2.4
Name: traxgen
Version: 0.1.5
Summary: Trajectory ground truth generator for agentic frameworks
Author: anonymous
Author-email: 
Requires-Python: >=3.8
License-File: LICENSE
Requires-Dist: networkx>=2.8
Requires-Dist: matplotlib>=3.5
Requires-Dist: seaborn>=0.11
Requires-Dist: pydantic>=1.10
Dynamic: author
Dynamic: description
Dynamic: description-content-type
Dynamic: license-file
Dynamic: requires-dist
Dynamic: requires-python
Dynamic: summary
